pandas_llm/__init__.py
pandas_llm/example-chatbot.py
pandas_llm/example.py
pandas_llm-0.0.6.dist-info/LICENSE
pandas_llm-0.0.6.dist-info/METADATA
pandas_llm-0.0.6.dist-info/WHEEL
pandas_llm-0.0.6.dist-info/top_level.txt
pandas_llm-0.0.6.dist-info/RECORD
