Metadata-Version: 2.1
Name: pandas-llm
Version: 0.0.6
Summary: Conversational Pandas Dataframes
Home-page: https://github.com/DashyDashOrg/pandas-llm
Download-URL: https://github.com/DashyDashOrg/pandas-llm/releases/tag/v0.0.6
Author: DashyDash
Author-email: alessio@dashydash.com
License: MIT
Project-URL: Bug Tracker, https://github.com/DashyDashOrg/pandas-llm/issues
Keywords: pypi,pandas-llm,pandas,llm,ai,openai,chatgpt
Classifier: Development Status :: 3 - Alpha
Classifier: Intended Audience :: Developers
Classifier: Topic :: Scientific/Engineering :: Artificial Intelligence
Classifier: License :: OSI Approved :: MIT License
Classifier: Programming Language :: Python :: 3
Classifier: Operating System :: OS Independent
Requires-Python: >=3.6
License-File: LICENSE
Requires-Dist: aiohttp
Requires-Dist: aiosignal
Requires-Dist: async-timeout
Requires-Dist: attrs
Requires-Dist: certifi
Requires-Dist: charset-normalizer
Requires-Dist: frozenlist
Requires-Dist: idna
Requires-Dist: multidict
Requires-Dist: numpy
Requires-Dist: openai
Requires-Dist: pandas
Requires-Dist: python-dateutil
Requires-Dist: pytz
Requires-Dist: requests
Requires-Dist: RestrictedPython
Requires-Dist: six
Requires-Dist: tqdm
Requires-Dist: tzdata
Requires-Dist: urllib3
Requires-Dist: yarl
